pyrotation/__init__.py
pyrotation/conversion.py
pyrotation/core.py
pyrotation/quaternions.py
pyrotation-0.0.2.dist-info/METADATA
pyrotation-0.0.2.dist-info/WHEEL
pyrotation-0.0.2.dist-info/licenses/LICENSE
pyrotation-0.0.2.dist-info/RECORD
