Metadata-Version: 2.1
Name: pyrotation
Version: 0.0.2
Summary: A package to handle rotation in 3D space with pytorch and numpy
Project-URL: Homepage, https://github.com/fzhiheng/pyrotation.git
Author-email: fzhiheng <fzhazr@sjtu.edu.cn>
Maintainer-email: fzhiheng <fzhazr@sjtu.edu.cn>
License-File: LICENSE
Keywords: SE3,SO3,axis-angle,euler,lie algebra,numpy,pytorch,quaternion,rotation,se3,so3
Classifier: Development Status :: 4 - Beta
Classifier: Intended Audience :: Science/Research
Classifier: License :: OSI Approved :: MIT License
Classifier: Operating System :: OS Independent
Classifier: Programming Language :: Python :: 3
Requires-Dist: numpy
Requires-Dist: plum-dispatch
Requires-Dist: torch
